README.md
setup.cfg
setup.py
distributions/Binomialdistribution.py
distributions/Gaussiandistribution.py
distributions/Generaldistribution.py
distributions/__init__.py
distributions_jair.egg-info/PKG-INFO
distributions_jair.egg-info/SOURCES.txt
distributions_jair.egg-info/dependency_links.txt
distributions_jair.egg-info/not-zip-safe
distributions_jair.egg-info/top_level.txt