Metadata-Version: 1.0
Name: distributions-jair
Version: 0.1
Summary: Gaussian distributions Jair
Home-page: UNKNOWN
Author: UNKNOWN
Author-email: UNKNOWN
License: UNKNOWN
Platform: UNKNOWN
